Workbook

Sheet Settings
A1: Attendance, Leave & Payroll System
A3: Company Name | B3: ERGO ASIA INC. | D3: Code | E3: Meaning
A4: Payroll Month Start | B4: 46204 | D4: P | E4: Present
A5: Monthly CL Earned | B5: 0 | D5: A | E5: Absent / LWP
A6: Monthly EL Earned | B6: 1 | D6: CL | E6: Casual Leave
A7: Default Professional Tax | B7: 200 | D7: EL | E7: Earned Leave
A8: Default PF Deduction | B8: 0 | D8: H | E8: Paid Holiday
A9: Default TDS | B9: 0 | D9: WO | E9: Weekly Off
A10: Status Codes | B10: P, A, CL, EL, H, WO, HD, LWP | D10: HD | E10: Half Day Present
D11: LWP | E11: Leave Without Pay

Sheet Employee_Master
A1: Emp ID | B1: Employee Name | C1: Date of Joining | D1: Designation | E1: PAN | F1: Bank Account No. | G1: Bank Name / IFSC | H1: Opening CL | I1: Opening EL | J1: Basic | K1: HRA | L1: Education Allowance | M1: Conveyance | N1: Professional Development | O1: Other Allowance | P1: LTA | Q1: Employer PF | R1: Bonus | S1: PF Deduction | T1: Professional Tax | U1: TDS | V1: Active?
A2: 4 | B2: Sumit Sunil Chirmade | C2: 45419 | D2: Assistant Manager - NPD & Purchase | E2: BAEPC0565P | F2: 50100626527431 | G2: HDFC Bank Limited Shirval (IFSC: HDFC0003543) | H2: 0 | I2: 0 | J2: 27500 | K2: 11000 | L2: 200 | M2: 1600 | N2: 2200 | O2: 8250 | P2: 3497 | Q2: 3300 | R2: 0 | S2: 0 | T2: 0 | U2: 0 | V2: No
A3: 9 | B3: Mahesh Swami | C3: 46146 | D3: Asst Manager Purchase & NPD | E3: FIZPS4652A | F3: 918010053106200 | G3: Axis Bank (UTIB0000037) | H3: 6 | I3: 2 | J3: 20000 | K3: 8000 | L3: 200 | M3: 1600 | N3: 2000 | O3: 11000 | P3: 3179 | Q3: 2400 | R3: 12000 | S3: 0 | T3: 200 | U3: 0 | V3: Yes

Sheet Daily_Attendance
A1: Emp ID | B1: Employee Name | C1: Designation | D1: =IF(MONTH(Settings!$B$4+0)=MONTH(Settings!$B$4),Settings!$B$4+0,"") -> 46204 | E1: =IF(MONTH(Settings!$B$4+1)=MONTH(Settings!$B$4),Settings!$B$4+1,"") -> 46205 | F1: =IF(MONTH(Settings!$B$4+2)=MONTH(Settings!$B$4),Settings!$B$4+2,"") -> 46206 | G1: =IF(MONTH(Settings!$B$4+3)=MONTH(Settings!$B$4),Settings!$B$4+3,"") -> 46207 | H1: =IF(MONTH(Settings!$B$4+4)=MONTH(Settings!$B$4),Settings!$B$4+4,"") -> 46208 | I1: =IF(MONTH(Settings!$B$4+5)=MONTH(Settings!$B$4),Settings!$B$4+5,"") -> 46209 | J1: =IF(MONTH(Settings!$B$4+6)=MONTH(Settings!$B$4),Settings!$B$4+6,"") -> 46210 | K1: =IF(MONTH(Settings!$B$4+7)=MONTH(Settings!$B$4),Settings!$B$4+7,"") -> 46211 | L1: =IF(MONTH(Settings!$B$4+8)=MONTH(Settings!$B$4),Settings!$B$4+8,"") -> 46212 | M1: =IF(MONTH(Settings!$B$4+9)=MONTH(Settings!$B$4),Settings!$B$4+9,"") -> 46213 | N1: =IF(MONTH(Settings!$B$4+10)=MONTH(Settings!$B$4),Settings!$B$4+10,"") -> 46214 | O1: =IF(MONTH(Settings!$B$4+11)=MONTH(Settings!$B$4),Settings!$B$4+11,"") -> 46215 | P1: =IF(MONTH(Settings!$B$4+12)=MONTH(Settings!$B$4),Settings!$B$4+12,"") -> 46216 | Q1: =IF(MONTH(Settings!$B$4+13)=MONTH(Settings!$B$4),Settings!$B$4+13,"") -> 46217 | R1: =IF(MONTH(Settings!$B$4+14)=MONTH(Settings!$B$4),Settings!$B$4+14,"") -> 46218 | S1: =IF(MONTH(Settings!$B$4+15)=MONTH(Settings!$B$4),Settings!$B$4+15,"") -> 46219 | T1: =IF(MONTH(Settings!$B$4+16)=MONTH(Settings!$B$4),Settings!$B$4+16,"") -> 46220 | U1: =IF(MONTH(Settings!$B$4+17)=MONTH(Settings!$B$4),Settings!$B$4+17,"") -> 46221 | V1: =IF(MONTH(Settings!$B$4+18)=MONTH(Settings!$B$4),Settings!$B$4+18,"") -> 46222 | W1: =IF(MONTH(Settings!$B$4+19)=MONTH(Settings!$B$4),Settings!$B$4+19,"") -> 46223 | X1: =IF(MONTH(Settings!$B$4+20)=MONTH(Settings!$B$4),Settings!$B$4+20,"") -> 46224 | Y1: =IF(MONTH(Settings!$B$4+21)=MONTH(Settings!$B$4),Settings!$B$4+21,"") -> 46225 | Z1: =IF(MONTH(Settings!$B$4+22)=MONTH(Settings!$B$4),Settings!$B$4+22,"") -> 46226 | AA1: =IF(MONTH(Settings!$B$4+23)=MONTH(Settings!$B$4),Settings!$B$4+23,"") -> 46227 | AB1: =IF(MONTH(Settings!$B$4+24)=MONTH(Settings!$B$4),Settings!$B$4+24,"") -> 46228 | AC1: =IF(MONTH(Settings!$B$4+25)=MONTH(Settings!$B$4),Settings!$B$4+25,"") -> 46229 | AD1: =IF(MONTH(Settings!$B$4+26)=MONTH(Settings!$B$4),Settings!$B$4+26,"") -> 46230 | AE1: =IF(MONTH(Settings!$B$4+27)=MONTH(Settings!$B$4),Settings!$B$4+27,"") -> 46231 | AF1: =IF(MONTH(Settings!$B$4+28)=MONTH(Settings!$B$4),Settings!$B$4+28,"") -> 46232 | AG1: =IF(MONTH(Settings!$B$4+29)=MONTH(Settings!$B$4),Settings!$B$4+29,"") -> 46233 | AH1: =IF(MONTH(Settings!$B$4+30)=MONTH(Settings!$B$4),Settings!$B$4+30,"") -> 46234 | AI1: Present Days | AJ1: CL Taken | AK1: EL Taken | AL1: Paid Holidays/WO | AM1: Half Days | AN1: LWP/Absent | AO1: Paid Days
A2: =IF(Employee_Master!A2="","",Employee_Master!A2) -> 4 | B2: =IF(Employee_Master!B2="","",Employee_Master!B2) -> Sumit Sunil Chirmade | C2: =IF(Employee_Master!D2="","",Employee_Master!D2) -> Assistant Manager - NPD & Purchase | D2: A | E2: A | F2: A | G2: A | H2: A | I2: A | J2: A | K2: A | L2: A | M2: A | N2: A | O2: A | P2: A | Q2: A | R2: A | S2: A | T2: A | U2: A | V2: A | W2: A | X2: A | Y2: A | Z2: A | AA2: A | AB2: A | AC2: A | AD2: A | AE2: A | AF2: A | AG2: A | AI2: =IF($A2="","",COUNTIF(D2:AH2,"P") + 0.5*COUNTIF(D2:AH2,"HD")) -> 0 | AJ2: =IF($A2="","",COUNTIF(D2:AH2,"CL")) -> 0 | AK2: =IF($A2="","",COUNTIF(D2:AH2,"EL")) -> 0 | AL2: =IF($A2="","",COUNTIF(D2:AH2,"H")+COUNTIF(D2:AH2,"WO")) -> 0 | AM2: =IF($A2="","",COUNTIF(D2:AH2,"HD")) -> 0 | AN2: =IF($A2="","",COUNTIF(D2:AH2,"A")+COUNTIF(D2:AH2,"LWP")) -> 30 | AO2: =IF($A2="","",AI2+AJ2+AK2+AL2) -> 0
A3: =IF(Employee_Master!#REF!="","",Employee_Master!#REF!) -> #REF! | B3: =IF(Employee_Master!#REF!="","",Employee_Master!#REF!) -> #REF! | C3: =IF(Employee_Master!#REF!="","",Employee_Master!#REF!) -> #REF! | D3: P | E3: P | F3: P | G3: P | H3: P | I3: P | J3: P | K3: P | L3: P | M3: P | N3: P | O3: P | P3: P | Q3: P | R3: P | S3: P | T3: P | U3: P | V3: P | W3: P | X3: P | Y3: P | Z3: P | AA3: P | AB3: P | AC3: P | AD3: P | AE3: P | AF3: P | AG3: P | AH3: P | AI3: =IF($A3="","",COUNTIF(D3:AH3,"P") + 0.5*COUNTIF(D3:AH3,"HD")) -> #REF! | AJ3: =IF($A3="","",COUNTIF(D3:AH3,"CL")) -> #REF! | AK3: =IF($A3="","",COUNTIF(D3:AH3,"EL")) -> #REF! | AL3: =IF($A3="","",COUNTIF(D3:AH3,"H")+COUNTIF(D3:AH3,"WO")) -> #REF! | AM3: =IF($A3="","",COUNTIF(D3:AH3,"HD")) -> #REF! | AN3: =IF($A3="","",COUNTIF(D3:AH3,"A")+COUNTIF(D3:AH3,"LWP")) -> #REF! | AO3: =IF($A3="","",AI3+AJ3+AK3+AL3) -> #REF!
A4: =IF(Employee_Master!#REF!="","",Employee_Master!#REF!) -> #REF! | B4: =IF(Employee_Master!#REF!="","",Employee_Master!#REF!) -> #REF! | C4: =IF(Employee_Master!#REF!="","",Employee_Master!#REF!) -> #REF! | D4: P | E4: P | F4: P | G4: P | H4: P | I4: P | J4: P | K4: P | L4: P | M4: CL | N4: P | O4: P | P4: P | Q4: P | R4: P | S4: P | T4: P | U4: P | V4: P | W4: P | X4: P | Y4: P | Z4: P | AA4: P | AB4: P | AC4: P | AD4: P | AE4: P | AF4: P | AG4: P | AH4: P | AI4: =IF($A4="","",COUNTIF(D4:AH4,"P") + 0.5*COUNTIF(D4:AH4,"HD")) -> #REF! | AJ4: =IF($A4="","",COUNTIF(D4:AH4,"CL")) -> #REF! | AK4: =IF($A4="","",COUNTIF(D4:AH4,"EL")) -> #REF! | AL4: =IF($A4="","",COUNTIF(D4:AH4,"H")+COUNTIF(D4:AH4,"WO")) -> #REF! | AM4: =IF($A4="","",COUNTIF(D4:AH4,"HD")) -> #REF! | AN4: =IF($A4="","",COUNTIF(D4:AH4,"A")+COUNTIF(D4:AH4,"LWP")) -> #REF! | AO4: =IF($A4="","",AI4+AJ4+AK4+AL4) -> #REF!
A5: =IF(Employee_Master!#REF!="","",Employee_Master!#REF!) -> #REF! | B5: =IF(Employee_Master!#REF!="","",Employee_Master!#REF!) -> #REF! | C5: =IF(Employee_Master!#REF!="","",Employee_Master!#REF!) -> #REF! | D5: P | E5: P | F5: P | G5: P | H5: P | I5: P | J5: P | K5: P | L5: P | M5: P | N5: P | O5: P | P5: P | Q5: P | R5: P | S5: P | T5: P | U5: P | V5: P | W5: P | X5: P | Y5: P | Z5: P | AA5: P | AB5: P | AC5: P | AD5: P | AE5: P | AF5: P | AG5: P | AH5: P | AI5: =IF($A5="","",COUNTIF(D5:AH5,"P") + 0.5*COUNTIF(D5:AH5,"HD")) -> #REF! | AJ5: =IF($A5="","",COUNTIF(D5:AH5,"CL")) -> #REF! | AK5: =IF($A5="","",COUNTIF(D5:AH5,"EL")) -> #REF! | AL5: =IF($A5="","",COUNTIF(D5:AH5,"H")+COUNTIF(D5:AH5,"WO")) -> #REF! | AM5: =IF($A5="","",COUNTIF(D5:AH5,"HD")) -> #REF! | AN5: =IF($A5="","",COUNTIF(D5:AH5,"A")+COUNTIF(D5:AH5,"LWP")) -> #REF! | AO5: =IF($A5="","",AI5+AJ5+AK5+AL5) -> #REF!
A6: =IF(Employee_Master!A3="","",Employee_Master!A3) -> 9 | B6: =IF(Employee_Master!B3="","",Employee_Master!B3) -> Mahesh Swami | C6: =IF(Employee_Master!D3="","",Employee_Master!D3) -> Asst Manager Purchase & NPD | D6: P | E6: P | F6: P | G6: P | H6: P | I6: P | J6: P | K6: P | L6: P | M6: P | N6: P | O6: P | P6: P | Q6: P | R6: P | S6: P | T6: P | U6: P | V6: P | W6: P | X6: P | Y6: P | Z6: P | AA6: P | AB6: P | AC6: P | AD6: P | AE6: P | AF6: P | AG6: P | AH6: P | AI6: =IF($A6="","",COUNTIF(D6:AH6,"P") + 0.5*COUNTIF(D6:AH6,"HD")) -> 31 | AJ6: =IF($A6="","",COUNTIF(D6:AH6,"CL")) -> 0 | AK6: =IF($A6="","",COUNTIF(D6:AH6,"EL")) -> 0 | AL6: =IF($A6="","",COUNTIF(D6:AH6,"H")+COUNTIF(D6:AH6,"WO")) -> 0 | AM6: =IF($A6="","",COUNTIF(D6:AH6,"HD")) -> 0 | AN6: =IF($A6="","",COUNTIF(D6:AH6,"A")+COUNTIF(D6:AH6,"LWP")) -> 0 | AO6: =IF($A6="","",AI6+AJ6+AK6+AL6) -> 31
A7: =IF(Employee_Master!#REF!="","",Employee_Master!#REF!) -> #REF! | B7: =IF(Employee_Master!#REF!="","",Employee_Master!#REF!) -> #REF! | C7: =IF(Employee_Master!#REF!="","",Employee_Master!#REF!) -> #REF! | D7: P | E7: P | F7: P | G7: P | H7: P | I7: P | J7: P | K7: P | L7: P | M7: P | N7: P | O7: P | P7: P | Q7: P | R7: P | S7: P | T7: P | U7: P | V7: P | W7: P | X7: P | Y7: P | Z7: P | AA7: P | AB7: P | AC7: P | AD7: P | AE7: P | AF7: P | AG7: P | AH7: P | AI7: =IF($A7="","",COUNTIF(D7:AH7,"P") + 0.5*COUNTIF(D7:AH7,"HD")) -> #REF! | AJ7: =IF($A7="","",COUNTIF(D7:AH7,"CL")) -> #REF! | AK7: =IF($A7="","",COUNTIF(D7:AH7,"EL")) -> #REF! | AL7: =IF($A7="","",COUNTIF(D7:AH7,"H")+COUNTIF(D7:AH7,"WO")) -> #REF! | AM7: =IF($A7="","",COUNTIF(D7:AH7,"HD")) -> #REF! | AN7: =IF($A7="","",COUNTIF(D7:AH7,"A")+COUNTIF(D7:AH7,"LWP")) -> #REF! | AO7: =IF($A7="","",AI7+AJ7+AK7+AL7) -> #REF!
A8: =IF(Employee_Master!#REF!="","",Employee_Master!#REF!) -> #REF! | B8: =IF(Employee_Master!#REF!="","",Employee_Master!#REF!) -> #REF! | C8: =IF(Employee_Master!#REF!="","",Employee_Master!#REF!) -> #REF! | D8: P | E8: P | F8: P | G8: P | H8: P | I8: P | J8: P | K8: P | L8: P | M8: P | N8: P | O8: P | P8: P | Q8: P | R8: P | S8: P | T8: P | U8: P | V8: P | W8: P | X8: P | Y8: P | Z8: P | AA8: P | AB8: P | AC8: P | AD8: P | AE8: P | AF8: P | AG8: P | AH8: P | AI8: =IF($A8="","",COUNTIF(D8:AH8,"P") + 0.5*COUNTIF(D8:AH8,"HD")) -> #REF! | AJ8: =IF($A8="","",COUNTIF(D8:AH8,"CL")) -> #REF! | AK8: =IF($A8="","",COUNTIF(D8:AH8,"EL")) -> #REF! | AL8: =IF($A8="","",COUNTIF(D8:AH8,"H")+COUNTIF(D8:AH8,"WO")) -> #REF! | AM8: =IF($A8="","",COUNTIF(D8:AH8,"HD")) -> #REF! | AN8: =IF($A8="","",COUNTIF(D8:AH8,"A")+COUNTIF(D8:AH8,"LWP")) -> #REF! | AO8: =IF($A8="","",AI8+AJ8+AK8+AL8) -> #REF!
A9: =IF(Employee_Master!#REF!="","",Employee_Master!#REF!) -> #REF! | B9: =IF(Employee_Master!#REF!="","",Employee_Master!#REF!) -> #REF! | C9: =IF(Employee_Master!#REF!="","",Employee_Master!#REF!) -> #REF! | D9: P | E9: P | F9: P | G9: P | H9: P | I9: P | J9: P | K9: P | L9: P | M9: P | N9: P | O9: P | P9: P | Q9: P | R9: P | S9: P | T9: P | U9: P | V9: P | W9: P | X9: P | Y9: P | Z9: P | AA9: P | AB9: P | AC9: P | AD9: P | AE9: P | AF9: P | AG9: P | AI9: =IF($A9="","",COUNTIF(D9:AH9,"P") + 0.5*COUNTIF(D9:AH9,"HD")) -> #REF! | AJ9: =IF($A9="","",COUNTIF(D9:AH9,"CL")) -> #REF! | AK9: =IF($A9="","",COUNTIF(D9:AH9,"EL")) -> #REF! | AL9: =IF($A9="","",COUNTIF(D9:AH9,"H")+COUNTIF(D9:AH9,"WO")) -> #REF! | AM9: =IF($A9="","",COUNTIF(D9:AH9,"HD")) -> #REF! | AN9: =IF($A9="","",COUNTIF(D9:AH9,"A")+COUNTIF(D9:AH9,"LWP")) -> #REF! | AO9: =IF($A9="","",AI9+AJ9+AK9+AL9) -> #REF!
A10: =IF(Employee_Master!#REF!="","",Employee_Master!#REF!) -> #REF! | B10: =IF(Employee_Master!#REF!="","",Employee_Master!#REF!) -> #REF! | C10: =IF(Employee_Master!#REF!="","",Employee_Master!#REF!) -> #REF! | D10: P | E10: P | F10: P | G10: P | H10: P | I10: P | J10: P | K10: P | L10: P | M10: P | N10: P | O10: P | P10: P | Q10: P | R10: P | S10: P | T10: P | U10: P | V10: P | W10: P | X10: P | Y10: P | Z10: P | AA10: P | AB10: P | AC10: P | AD10: P | AE10: P | AF10: P | AG10: P | AI10: =IF($A10="","",COUNTIF(D10:AH10,"P") + 0.5*COUNTIF(D10:AH10,"HD")) -> #REF! | AJ10: =IF($A10="","",COUNTIF(D10:AH10,"CL")) -> #REF! | AK10: =IF($A10="","",COUNTIF(D10:AH10,"EL")) -> #REF! | AL10: =IF($A10="","",COUNTIF(D10:AH10,"H")+COUNTIF(D10:AH10,"WO")) -> #REF! | AM10: =IF($A10="","",COUNTIF(D10:AH10,"HD")) -> #REF! | AN10: =IF($A10="","",COUNTIF(D10:AH10,"A")+COUNTIF(D10:AH10,"LWP")) -> #REF! | AO10: =IF($A10="","",AI10+AJ10+AK10+AL10) -> #REF!
A11: =IF(Employee_Master!A4="","",Employee_Master!A4) | B11: =IF(Employee_Master!B4="","",Employee_Master!B4) | C11: =IF(Employee_Master!D4="","",Employee_Master!D4) | AI11: =IF($A11="","",COUNTIF(D11:AH11,"P") + 0.5*COUNTIF(D11:AH11,"HD")) | AJ11: =IF($A11="","",COUNTIF(D11:AH11,"CL")) | AK11: =IF($A11="","",COUNTIF(D11:AH11,"EL")) | AL11: =IF($A11="","",COUNTIF(D11:AH11,"H")+COUNTIF(D11:AH11,"WO")) | AM11: =IF($A11="","",COUNTIF(D11:AH11,"HD")) | AN11: =IF($A11="","",COUNTIF(D11:AH11,"A")+COUNTIF(D11:AH11,"LWP")) | AO11: =IF($A11="","",AI11+AJ11+AK11+AL11)
A12: =IF(Employee_Master!A5="","",Employee_Master!A5) | B12: =IF(Employee_Master!B5="","",Employee_Master!B5) | C12: =IF(Employee_Master!D5="","",Employee_Master!D5) | AI12: =IF($A12="","",COUNTIF(D12:AH12,"P") + 0.5*COUNTIF(D12:AH12,"HD")) | AJ12: =IF($A12="","",COUNTIF(D12:AH12,"CL")) | AK12: =IF($A12="","",COUNTIF(D12:AH12,"EL")) | AL12: =IF($A12="","",COUNTIF(D12:AH12,"H")+COUNTIF(D12:AH12,"WO")) | AM12: =IF($A12="","",COUNTIF(D12:AH12,"HD")) | AN12: =IF($A12="","",COUNTIF(D12:AH12,"A")+COUNTIF(D12:AH12,"LWP")) | AO12: =IF($A12="","",AI12+AJ12+AK12+AL12)
A13: =IF(Employee_Master!A6="","",Employee_Master!A6) | B13: =IF(Employee_Master!B6="","",Employee_Master!B6) | C13: =IF(Employee_Master!D6="","",Employee_Master!D6) | AI13: =IF($A13="","",COUNTIF(D13:AH13,"P") + 0.5*COUNTIF(D13:AH13,"HD")) | AJ13: =IF($A13="","",COUNTIF(D13:AH13,"CL")) | AK13: =IF($A13="","",COUNTIF(D13:AH13,"EL")) | AL13: =IF($A13="","",COUNTIF(D13:AH13,"H")+COUNTIF(D13:AH13,"WO")) | AM13: =IF($A13="","",COUNTIF(D13:AH13,"HD")) | AN13: =IF($A13="","",COUNTIF(D13:AH13,"A")+COUNTIF(D13:AH13,"LWP")) | AO13: =IF($A13="","",AI13+AJ13+AK13+AL13)
A14: =IF(Employee_Master!A7="","",Employee_Master!A7) | B14: =IF(Employee_Master!B7="","",Employee_Master!B7) | C14: =IF(Employee_Master!D7="","",Employee_Master!D7) | AI14: =IF($A14="","",COUNTIF(D14:AH14,"P") + 0.5*COUNTIF(D14:AH14,"HD")) | AJ14: =IF($A14="","",COUNTIF(D14:AH14,"CL")) | AK14: =IF($A14="","",COUNTIF(D14:AH14,"EL")) | AL14: =IF($A14="","",COUNTIF(D14:AH14,"H")+COUNTIF(D14:AH14,"WO")) | AM14: =IF($A14="","",COUNTIF(D14:AH14,"HD")) | AN14: =IF($A14="","",COUNTIF(D14:AH14,"A")+COUNTIF(D14:AH14,"LWP")) | AO14: =IF($A14="","",AI14+AJ14+AK14+AL14)
A15: =IF(Employee_Master!#REF!="","",Employee_Master!#REF!) -> #REF! | B15: =IF(Employee_Master!#REF!="","",Employee_Master!#REF!) -> #REF! | C15: =IF(Employee_Master!#REF!="","",Employee_Master!#REF!) -> #REF! | AI15: =IF($A15="","",COUNTIF(D15:AH15,"P") + 0.5*COUNTIF(D15:AH15,"HD")) -> #REF! | AJ15: =IF($A15="","",COUNTIF(D15:AH15,"CL")) -> #REF! | AK15: =IF($A15="","",COUNTIF(D15:AH15,"EL")) -> #REF! | AL15: =IF($A15="","",COUNTIF(D15:AH15,"H")+COUNTIF(D15:AH15,"WO")) -> #REF! | AM15: =IF($A15="","",COUNTIF(D15:AH15,"HD")) -> #REF! | AN15: =IF($A15="","",COUNTIF(D15:AH15,"A")+COUNTIF(D15:AH15,"LWP")) -> #REF! | AO15: =IF($A15="","",AI15+AJ15+AK15+AL15) -> #REF!
A16: =IF(Employee_Master!#REF!="","",Employee_Master!#REF!) -> #REF! | B16: =IF(Employee_Master!#REF!="","",Employee_Master!#REF!) -> #REF! | C16: =IF(Employee_Master!#REF!="","",Employee_Master!#REF!) -> #REF! | AI16: =IF($A16="","",COUNTIF(D16:AH16,"P") + 0.5*COUNTIF(D16:AH16,"HD")) -> #REF! | AJ16: =IF($A16="","",COUNTIF(D16:AH16,"CL")) -> #REF! | AK16: =IF($A16="","",COUNTIF(D16:AH16,"EL")) -> #REF! | AL16: =IF($A16="","",COUNTIF(D16:AH16,"H")+COUNTIF(D16:AH16,"WO")) -> #REF! | AM16: =IF($A16="","",COUNTIF(D16:AH16,"HD")) -> #REF! | AN16: =IF($A16="","",COUNTIF(D16:AH16,"A")+COUNTIF(D16:AH16,"LWP")) -> #REF! | AO16: =IF($A16="","",AI16+AJ16+AK16+AL16) -> #REF!
A17: =IF(Employee_Master!A4="","",Employee_Master!A4) | B17: =IF(Employee_Master!B4="","",Employee_Master!B4) | C17: =IF(Employee_Master!D4="","",Employee_Master!D4) | AI17: =IF($A17="","",COUNTIF(D17:AH17,"P") + 0.5*COUNTIF(D17:AH17,"HD")) | AJ17: =IF($A17="","",COUNTIF(D17:AH17,"CL")) | AK17: =IF($A17="","",COUNTIF(D17:AH17,"EL")) | AL17: =IF($A17="","",COUNTIF(D17:AH17,"H")+COUNTIF(D17:AH17,"WO")) | AM17: =IF($A17="","",COUNTIF(D17:AH17,"HD")) | AN17: =IF($A17="","",COUNTIF(D17:AH17,"A")+COUNTIF(D17:AH17,"LWP")) | AO17: =IF($A17="","",AI17+AJ17+AK17+AL17)
A18: =IF(Employee_Master!A5="","",Employee_Master!A5) | B18: =IF(Employee_Master!B5="","",Employee_Master!B5) | C18: =IF(Employee_Master!D5="","",Employee_Master!D5) | AI18: =IF($A18="","",COUNTIF(D18:AH18,"P") + 0.5*COUNTIF(D18:AH18,"HD")) | AJ18: =IF($A18="","",COUNTIF(D18:AH18,"CL")) | AK18: =IF($A18="","",COUNTIF(D18:AH18,"EL")) | AL18: =IF($A18="","",COUNTIF(D18:AH18,"H")+COUNTIF(D18:AH18,"WO")) | AM18: =IF($A18="","",COUNTIF(D18:AH18,"HD")) | AN18: =IF($A18="","",COUNTIF(D18:AH18,"A")+COUNTIF(D18:AH18,"LWP")) | AO18: =IF($A18="","",AI18+AJ18+AK18+AL18)
A19: =IF(Employee_Master!A6="","",Employee_Master!A6) | B19: =IF(Employee_Master!B6="","",Employee_Master!B6) | C19: =IF(Employee_Master!D6="","",Employee_Master!D6) | AI19: =IF($A19="","",COUNTIF(D19:AH19,"P") + 0.5*COUNTIF(D19:AH19,"HD")) | AJ19: =IF($A19="","",COUNTIF(D19:AH19,"CL")) | AK19: =IF($A19="","",COUNTIF(D19:AH19,"EL")) | AL19: =IF($A19="","",COUNTIF(D19:AH19,"H")+COUNTIF(D19:AH19,"WO")) | AM19: =IF($A19="","",COUNTIF(D19:AH19,"HD")) | AN19: =IF($A19="","",COUNTIF(D19:AH19,"A")+COUNTIF(D19:AH19,"LWP")) | AO19: =IF($A19="","",AI19+AJ19+AK19+AL19)
A20: =IF(Employee_Master!A7="","",Employee_Master!A7) | B20: =IF(Employee_Master!B7="","",Employee_Master!B7) | C20: =IF(Employee_Master!D7="","",Employee_Master!D7) | AI20: =IF($A20="","",COUNTIF(D20:AH20,"P") + 0.5*COUNTIF(D20:AH20,"HD")) | AJ20: =IF($A20="","",COUNTIF(D20:AH20,"CL")) | AK20: =IF($A20="","",COUNTIF(D20:AH20,"EL")) | AL20: =IF($A20="","",COUNTIF(D20:AH20,"H")+COUNTIF(D20:AH20,"WO")) | AM20: =IF($A20="","",COUNTIF(D20:AH20,"HD")) | AN20: =IF($A20="","",COUNTIF(D20:AH20,"A")+COUNTIF(D20:AH20,"LWP")) | AO20: =IF($A20="","",AI20+AJ20+AK20+AL20)
A21: =IF(Employee_Master!#REF!="","",Employee_Master!#REF!) -> #REF! | B21: =IF(Employee_Master!#REF!="","",Employee_Master!#REF!) -> #REF! | C21: =IF(Employee_Master!#REF!="","",Employee_Master!#REF!) -> #REF! | AI21: =IF($A21="","",COUNTIF(D21:AH21,"P") + 0.5*COUNTIF(D21:AH21,"HD")) -> #REF! | AJ21: =IF($A21="","",COUNTIF(D21:AH21,"CL")) -> #REF! | AK21: =IF($A21="","",COUNTIF(D21:AH21,"EL")) -> #REF! | AL21: =IF($A21="","",COUNTIF(D21:AH21,"H")+COUNTIF(D21:AH21,"WO")) -> #REF! | AM21: =IF($A21="","",COUNTIF(D21:AH21,"HD")) -> #REF! | AN21: =IF($A21="","",COUNTIF(D21:AH21,"A")+COUNTIF(D21:AH21,"LWP")) -> #REF! | AO21: =IF($A21="","",AI21+AJ21+AK21+AL21) -> #REF!

Sheet Leave_Register
A1: Month | B1: Emp ID | C1: Employee Name | D1: Opening CL | E1: CL Earned | F1: CL Taken | G1: Closing CL | H1: Opening EL | I1: EL Earned | J1: EL Taken | K1: Closing EL | L1: LWP/Absent
A2: =Settings!$B$4 -> 46204 | B2: =IF(Employee_Master!A2="","",Employee_Master!A2) -> 4 | C2: =IF(Employee_Master!B2="","",Employee_Master!B2) -> Sumit Sunil Chirmade | D2: =IF(B2="","",Employee_Master!H2) -> 0 | E2: =IF(B2="","",Settings!$B$5) -> 0 | F2: =IF(B2="","",Daily_Attendance!AJ2) -> 0 | G2: =IF(B2="","",D2+E2-F2) -> 0 | H2: =IF(B2="","",Employee_Master!I2) -> 0 | I2: =IF(B2="","",Settings!$B$6) -> 1 | J2: =IF(B2="","",Daily_Attendance!AK2) -> 0 | K2: =IF(B2="","",H2+I2-J2) -> 1 | L2: =IF(B2="","",Daily_Attendance!AN2) -> 30
A3: =Settings!$B$4 -> 46204 | B3: =IF(Employee_Master!A3="","",Employee_Master!A3) -> 9 | C3: =IF(Employee_Master!B3="","",Employee_Master!B3) -> Mahesh Swami | D3: =IF(B3="","",Employee_Master!H3) -> 6 | E3: =IF(B3="","",Settings!$B$5) -> 0 | F3: =IF(B3="","",Daily_Attendance!AJ6) -> 0 | G3: =IF(B3="","",D3+E3-F3) -> 6 | H3: =IF(B3="","",Employee_Master!I3) -> 2 | I3: =IF(B3="","",Settings!$B$6) -> 1 | J3: =IF(B3="","",Daily_Attendance!AK6) -> 0 | K3: =IF(B3="","",H3+I3-J3) -> 3 | L3: =IF(B3="","",Daily_Attendance!AN6) -> 0

Sheet Monthly_Payroll
A1: Month | B1: Emp ID | C1: Employee Name | D1: Designation | E1: Total Days | F1: Paid Days | G1: Basic | H1: HRA | I1: Education | J1: Conveyance | K1: Prof Dev | L1: Other Allow | M1: LTA | N1: Employer PF | O1: Bonus | P1: Gross Income | Q1: PF Ded | R1: Professional Tax | S1: TDS | T1: Total Deduction | U1: Net Salary
A2: =Settings!$B$4 -> 46204 | B2: =IF(Employee_Master!A2="","",Employee_Master!A2) -> 4 | C2: =IF(Employee_Master!B2="","",Employee_Master!B2) -> Sumit Sunil Chirmade | D2: =IF(Employee_Master!D2="","",Employee_Master!D2) -> Assistant Manager - NPD & Purchase | E2: =DAY(EOMONTH(Settings!$B$4,0)) -> 31 | F2: =IF(B2="","",Daily_Attendance!AO2) -> 0 | G2: =IF(B2="","",ROUND(Employee_Master!J2*F2/E2,0)) -> 0 | H2: =IF(B2="","",ROUND(Employee_Master!K2*F2/E2,0)) -> 0 | I2: =IF(B2="","",ROUND(Employee_Master!L2*F2/E2,0)) -> 0 | J2: =IF(B2="","",ROUND(Employee_Master!M2*F2/E2,0)) -> 0 | K2: =IF(B2="","",ROUND(Employee_Master!N2*F2/E2,0)) -> 0 | L2: =IF(B2="","",ROUND(Employee_Master!O2*F2/E2,0)) -> 0 | M2: =IF(B2="","",ROUND(Employee_Master!P2*F2/E2,0)) -> 0 | N2: =IF(B2="","",ROUND(Employee_Master!Q2*F2/E2,0)) -> 0 | O2: =IF(B2="","",Employee_Master!R2) -> 0 | P2: =IF(B2="","",SUM(G2:O2)) -> 0 | Q2: =IF(B2="","",Employee_Master!S2) -> 0 | R2: =IF(B2="","",Employee_Master!T2) -> 0 | S2: =IF(B2="","",Employee_Master!U2) -> 0 | T2: =IF(B2="","",SUM(Q2:S2)) -> 0 | U2: =IF(B2="","",P2-T2) -> 0
A3: =Settings!$B$4 -> 46204 | B3: =IF(Employee_Master!A3="","",Employee_Master!A3) -> 9 | C3: =IF(Employee_Master!B3="","",Employee_Master!B3) -> Mahesh Swami | D3: =IF(Employee_Master!D3="","",Employee_Master!D3) -> Asst Manager Purchase & NPD | E3: =DAY(EOMONTH(Settings!$B$4,0)) -> 31 | F3: =IF(B3="","",Daily_Attendance!AO6) -> 31 | G3: =IF(B3="","",ROUND(Employee_Master!J3*F3/E3,0)) -> 20000 | H3: =IF(B3="","",ROUND(Employee_Master!K3*F3/E3,0)) -> 8000 | I3: =IF(B3="","",ROUND(Employee_Master!L3*F3/E3,0)) -> 200 | J3: =IF(B3="","",ROUND(Employee_Master!M3*F3/E3,0)) -> 1600 | K3: =IF(B3="","",ROUND(Employee_Master!N3*F3/E3,0)) -> 2000 | L3: =IF(B3="","",ROUND(Employee_Master!O3*F3/E3,0)) -> 11000 | M3: =IF(B3="","",ROUND(Employee_Master!P3*F3/E3,0)) -> 3179 | N3: =IF(B3="","",ROUND(Employee_Master!Q3*F3/E3,0)) -> 2400 | O3: 0 | P3: =IF(B3="","",SUM(G3:O3)) -> 48379 | Q3: =IF(B3="","",Employee_Master!S3) -> 0 | R3: =IF(B3="","",Employee_Master!T3) -> 200 | S3: =IF(B3="","",Employee_Master!U3) -> 0 | T3: =IF(B3="","",SUM(Q3:S3)) -> 200 | U3: =IF(B3="","",P3-T3) -> 48179
P4: =#REF!/2 -> #REF!

Sheet Payslip
A1: Select Employee ID | B1: 10
A3: =Settings!$B$3 -> ERGO ASIA INC.
A4: SALARY SLIP
A6: MONTH | B6: =TEXT(Settings!$B$4,"mmmm-yy") -> July-26
A7: Employee Name | B7: =IFERROR(INDEX(Employee_Master!$B$2:$B$20,MATCH($B$1,Employee_Master!$A$2:$A$20,0)),"") | C7: Date of Joining | D7: =IFERROR(INDEX(Employee_Master!$C$2:$C$20,MATCH($B$1,Employee_Master!$A$2:$A$20,0)),"")
A8: Employee Code | B8: =$B$1 -> 10 | C8: Total no of days | D8: =IFERROR(INDEX(Monthly_Payroll!$E$2:$E$3,MATCH($B$1,Monthly_Payroll!$B$2:$B$3,0)),"")
A9: Designation | B9: =IFERROR(INDEX(Employee_Master!$D$2:$D$20,MATCH($B$1,Employee_Master!$A$2:$A$20,0)),"") | C9: No of days attended | D9: =IFERROR(INDEX(Monthly_Payroll!$F$2:$F$3,MATCH($B$1,Monthly_Payroll!$B$2:$B$3,0)),"")
A10: PAN number | B10: =IFERROR(INDEX(Employee_Master!$E$2:$E$20,MATCH($B$1,Employee_Master!$A$2:$A$20,0)),"") | C10: Leaves
A11: Bank Account Number | B11: =IFERROR(INDEX(Employee_Master!$F$2:$F$20,MATCH($B$1,Employee_Master!$A$2:$A$20,0)),"") | C11: Previous CL + EL | D11: =IFERROR(INDEX(Leave_Register!$D$2:$D$3,MATCH($B$1,Leave_Register!$B$2:$B$3,0)),0)+IFERROR(INDEX(Leave_Register!$H$2:$H$3,MATCH($B$1,Leave_Register!$B$2:$B$3,0)),0) -> 0
A12: Bank Name | B12: =IFERROR(INDEX(Employee_Master!$G$2:$G$20,MATCH($B$1,Employee_Master!$A$2:$A$20,0)),"") | C12: Leave earned this month | D12: =IFERROR(INDEX(Leave_Register!$E$2:$E$3,MATCH($B$1,Leave_Register!$B$2:$B$3,0)),0)+IFERROR(INDEX(Leave_Register!$I$2:$I$3,MATCH($B$1,Leave_Register!$B$2:$B$3,0)),0) -> 0
C13: Leave taken this month | D13: =IFERROR(INDEX(Leave_Register!$F$2:$F$3,MATCH($B$1,Leave_Register!$B$2:$B$3,0)),0)+IFERROR(INDEX(Leave_Register!$J$2:$J$3,MATCH($B$1,Leave_Register!$B$2:$B$3,0)),0) -> 0
C14: Net Balance | D14: =IFERROR(INDEX(Leave_Register!$G$2:$G$3,MATCH($B$1,Leave_Register!$B$2:$B$3,0)),0)+IFERROR(INDEX(Leave_Register!$K$2:$K$3,MATCH($B$1,Leave_Register!$B$2:$B$3,0)),0) -> 0
A16: Income | C16: Deductions
A17: Particulars | B17: Amount (INR) | C17: Particulars | D17: Amount (INR) | J17: 1585
A18: Basic | B18: =IFERROR(INDEX(Monthly_Payroll!$G$2:$G$3,MATCH($B$1,Monthly_Payroll!$B$2:$B$3,0)),0) -> 0 | C18: PF | D18: =IFERROR(INDEX(Monthly_Payroll!$Q$2:$Q$3,MATCH($B$1,Monthly_Payroll!$B$2:$B$3,0)),0) -> 0 | J18: 2
A19: House Rent Allowance | B19: =IFERROR(INDEX(Monthly_Payroll!$H$2:$H$3,MATCH($B$1,Monthly_Payroll!$B$2:$B$3,0)),0) -> 0 | C19: Professional Tax | D19: =IFERROR(INDEX(Monthly_Payroll!$R$2:$R$3,MATCH($B$1,Monthly_Payroll!$B$2:$B$3,0)),0) -> 0 | J19: =J17*J18 -> 3170
A20: Education Allowance | B20: =IFERROR(INDEX(Monthly_Payroll!$I$2:$I$3,MATCH($B$1,Monthly_Payroll!$B$2:$B$3,0)),0) -> 0 | C20: TDS | D20: =IFERROR(INDEX(Monthly_Payroll!$S$2:$S$3,MATCH($B$1,Monthly_Payroll!$B$2:$B$3,0)),0) -> 0
A21: Conveyance Allowance | B21: =IFERROR(INDEX(Monthly_Payroll!$J$2:$J$3,MATCH($B$1,Monthly_Payroll!$B$2:$B$3,0)),0) -> 0
A22: Professional Development allowance | B22: =IFERROR(INDEX(Monthly_Payroll!$K$2:$K$3,MATCH($B$1,Monthly_Payroll!$B$2:$B$3,0)),0) -> 0
A23: Other Allowance | B23: =IFERROR(INDEX(Monthly_Payroll!$L$2:$L$3,MATCH($B$1,Monthly_Payroll!$B$2:$B$3,0)),0) -> 0
A24: Leave Travel Allowance (LTA) | B24: =IFERROR(INDEX(Monthly_Payroll!$M$2:$M$3,MATCH($B$1,Monthly_Payroll!$B$2:$B$3,0)),0) -> 0
A25: PF(Employer contribution) | B25: =IFERROR(INDEX(Monthly_Payroll!$N$2:$N$3,MATCH($B$1,Monthly_Payroll!$B$2:$B$3,0)),0) -> 0
A26: Bonus | B26: =IFERROR(INDEX(Monthly_Payroll!$O$2:$O$3,MATCH($B$1,Monthly_Payroll!$B$2:$B$3,0)),0) -> 0
A27: Total | B27: =SUM(B18:B26) -> 0 | C27: Total | D27: =SUM(D18:D26) -> 0
A28: Net Salary | D28: =B27-D27 -> 0
C31: #VALUE!
A35: Employee signature | C35: Employer Signature

Sheet Dashboard
A1: Payroll Summary Dashboard
A3: Month | B3: =TEXT(Settings!$B$4,"mmmm-yy") -> July-26
A4: Active Employees | B4: =COUNTIF(Employee_Master!V2:V20,"Yes") -> 1
A5: Total Gross Salary | B5: =SUM(Monthly_Payroll!P2:P3) -> 48379
A6: Total Deductions | B6: =SUM(Monthly_Payroll!T2:T3) -> 200
A7: Total Net Salary | B7: =SUM(Monthly_Payroll!U2:U3) -> 48179
A8: Total Leave Taken | B8: =SUM(Leave_Register!F2:F3)+SUM(Leave_Register!J2:J3) -> 0
A10: Emp ID | B10: Employee Name | C10: Paid Days | D10: Leave Taken | E10: Net Salary
A11: =Monthly_Payroll!B2 -> 4 | B11: =Monthly_Payroll!C2 -> Sumit Sunil Chirmade | C11: =Monthly_Payroll!F2 -> 0 | D11: =Leave_Register!F2+Leave_Register!J2 -> 0 | E11: =Monthly_Payroll!U2 -> 0
A12: =Monthly_Payroll!B3 -> 9 | B12: =Monthly_Payroll!C3 -> Mahesh Swami | C12: =Monthly_Payroll!F3 -> 31 | D12: =Leave_Register!F3+Leave_Register!J3 -> 0 | E12: =Monthly_Payroll!U3 -> 48179
